LICENSE.3RDPARTY
MANIFEST.in
README.md
SECURITY.md
requirements.txt
setup.cfg
setup.py
django_multitenancy_manager.egg-info/PKG-INFO
django_multitenancy_manager.egg-info/SOURCES.txt
django_multitenancy_manager.egg-info/dependency_links.txt
django_multitenancy_manager.egg-info/entry_points.txt
django_multitenancy_manager.egg-info/not-zip-safe
django_multitenancy_manager.egg-info/requires.txt
django_multitenancy_manager.egg-info/top_level.txt
multitenancy/__init__.py
multitenancy/settings.py
multitenancy/urls.py
multitenancy/utils.py
multitenancy/admin/__init__.py
multitenancy/admin/admin.py
multitenancy/admin/apps.py
multitenancy/admin/customer_urls.py
multitenancy/admin/decorators.py
multitenancy/admin/filters.py
multitenancy/admin/forms.py
multitenancy/admin/models.py
multitenancy/admin/team_urls.py
multitenancy/admin/urls.py
multitenancy/admin/migrations/__init__.py
multitenancy/admin/views/__init__.py
multitenancy/admin/views/adminViews.py
multitenancy/admin/views/authViews.py
multitenancy/admin/views/baseViews.py
multitenancy/admin/views/customerViews.py
multitenancy/admin/views/teamViews.py
multitenancy/apps/__init__.py
multitenancy/apps/admin.py
multitenancy/apps/apps.py
multitenancy/apps/models.py
multitenancy/apps/views.py
multitenancy/apps/migrations/0001_initial.py
multitenancy/apps/migrations/0002_initial.py
multitenancy/apps/migrations/0003_auto_20221111_1809.py
multitenancy/apps/migrations/0004_rename_packages_package.py
multitenancy/apps/migrations/0005_alter_tenanttype_name.py
multitenancy/apps/migrations/0006_alter_tenant_type.py
multitenancy/apps/migrations/0007_tenant_subscription.py
multitenancy/apps/migrations/0008_auto_20221208_1033.py
multitenancy/apps/migrations/0009_domain_has_custom.py
multitenancy/apps/migrations/0010_auto_20221210_1524.py
multitenancy/apps/migrations/0011_auto_20230101_0650.py
multitenancy/apps/migrations/0012_auto_20230107_1742.py
multitenancy/apps/migrations/0013_alter_tenant_trail_duration.py
multitenancy/apps/migrations/0014_alter_tenant_subscription.py
multitenancy/apps/migrations/__init__.py
multitenancy/billing/__init__.py
multitenancy/billing/admin.py
multitenancy/billing/apps.py
multitenancy/billing/models.py
multitenancy/billing/tests.py
multitenancy/billing/views.py
multitenancy/billing/gateways/__init__.py
multitenancy/billing/migrations/__init__.py
